{
    "title": "Mom's Homestyle Barilla® Gluten Free Macaroni Salad",
    "ingredients": [
        "1 (12 ounce) box Barilla® Gluten Free Elbows",
        "2 boneless, skinless chicken breast halves",
        "salt and pepper to taste",
        "2 tablespoons olive oil, divided",
        "½ cup mayonnaise",
        "½ cup sour cream",
        "3 tablespoons red wine vinegar",
        "2 tablespoons sugar",
        "1 tablespoon celery seed",
        "½ cup diced celery",
        "3 large tomatoes, diced"
    ],
    "core_ingredients": [
        "gluten free elbows",
        "chicken breast",
        "mayonnaise",
        "sour cream",
        "celery",
        "tomatoes"
    ],
    "instructions": "1. Bring a large pot of water to a boil. 2. Meanwhile, season the chicken with salt & pepper and 1 tablespoon of olive oil. 3. Grill the chicken about 4 minutes per side or until fully cooked - set aside to cool. Cut into bite-size pieces. 4. Cook pasta according to package directions. 5. In a large bowl, combine the mayonnaise, sour cream, red wine vinegar, sugar and celery seed - stir to combine. Then, season with salt and pepper to taste. 6. Drain the pasta and toss with 1 tablespoon olive oil. 7. Once the pasta has slightly cooled, toss with the sauce and vegetables. 8. Top with grilled chicken & serve immediately - do not chill.",
    "tags": [
        "salad",
        "gluten free",
        "easy meal"
    ],
    "diet_type": "Gluten-Free",
    "cuisine": "American",
    "time_to_eat": 25,
    "suggestion_links": [
        "https://www.allrecipes.com/recipe/265787/gluten-free-chicken-pasta-salad/",
        "https://www.allrecipes.com/recipe/73920/pool-party-pasta-salad/",
        "https://www.allrecipes.com/recipe/71557/zesty-feta-and-shrimp-summer-pasta-salad/",
        "https://www.allrecipes.com/recipe/212932/filipino-chicken-salad/"
    ],
    "img_links": [
        "https://www.allrecipes.com/thmb/bLzemwdOa5xCpGIE4bhOvkJeVSo=/1500x0/filters:no_upscale():max_bytes(150000):strip_icc()/4511977-af7b5617ac5f436eaf68febd7edc5f25.jpg"
    ],
    "source_url": "https://www.allrecipes.com/recipe/258007/moms-homestyle-barilla-gluten-free-macaroni-salad/",
    "id": "9f0b9d3b-f1d4-4763-8968-7e9f1aebe0a3"
}