{
    "title": "Mom's Shrimp Macaroni Salad",
    "ingredients": [
        "1 cup uncooked elbow macaroni",
        "¾ cup mayonnaise",
        "½ cup diced celery",
        "¼ cup sweet pickle relish",
        "2 ounces cooked salad shrimp",
        "2 tablespoons ketchup",
        "2 tablespoons white wine vinegar",
        "1 tablespoon minced onion",
        "1 tablespoon chopped green bell pepper",
        "1 tablespoon chopped fresh parsley",
        "1 teaspoon prepared horseradish",
        "½ teaspoon celery seed",
        "¼ teaspoon hot pepper sauce",
        "⅛ teaspoon chili powder",
        "salt and ground black pepper to taste"
    ],
    "core_ingredients": [
        "elbow macaroni",
        "mayonnaise",
        "celery",
        "pickle relish",
        "shrimp",
        "ketchup",
        "vinegar"
    ],
    "instructions": "1. Bring a large pot of lightly salted water to a boil. Cook elbow macaroni in the boiling water, stirring occasionally, until tender yet firm to the bite, about 8 minutes. Drain well. 2. Combine mayonnaise, celery, relish, shrimp, ketchup, vinegar, onion, bell pepper, parsley, horseradish, celery seed, hot pepper sauce, chili powder, salt, and black pepper in a medium-sized bowl. Fold macaroni into mixture. Cover and chill at least 3 hours before serving.",
    "tags": [
        "Salad",
        "Seafood",
        "Macaroni"
    ],
    "diet_type": "Non-Vegetarian",
    "cuisine": "American",
    "time_to_eat": 210,
    "suggestion_links": [
        "https://www.allrecipes.com/recipe/87854/kahalas-macaroni-seafood-salad/",
        "https://www.allrecipes.com/recipe/238593/my-moms-awesome-macaroni-salad-enough-to-feed-a-crowd/",
        "https://www.allrecipes.com/recipe/11818/tangy-catalina-pasta-salad/",
        "https://www.allrecipes.com/recipe/21537/shrimp-vermicelli-salad/",
        "https://www.allrecipes.com/recipe/21664/shrimp-and-crab-macaroni-salad/"
    ],
    "img_links": [
        "https://www.allrecipes.com/thmb/iQEw5BPK3Yg2mg6-LCc87zdYJ88=/1500x0/filters:no_upscale():max_bytes(150000):strip_icc()/387386-204769a7ac1b42eda24f4117f80c1461.jpg"
    ],
    "source_url": "https://www.allrecipes.com/recipe/16859/moms-shrimp-macaroni-salad/",
    "id": "9fc3e4eb-89b1-4ffb-a81c-afb6a86d4618"
}