{
    "title": "Southern Peach Cobbler",
    "ingredients": [
        "½ cup butter",
        "1 cup white sugar",
        "¾ cup self-rising flour",
        "¾ cup milk",
        "1 (29 ounce) can sliced peaches in light syrup"
    ],
    "core_ingredients": [
        "butter",
        "sugar",
        "flour",
        "milk",
        "peaches"
    ],
    "instructions": "1. Preheat oven to 350 degrees F (175 degrees C). Place butter in a deep 2 quart baking dish and place in oven to melt. 2. In a medium bowl, mix sugar and flour. Stir in milk, a little at a time, until wholly incorporated. Pour carefully over melted butter in dish. Spoon peaches and syrup over batter. 3. Bake in preheated oven 35 to 45 minutes, until crust is puffed and golden.",
    "tags": [
        "dessert",
        "cobbler",
        "peach",
        "baking"
    ],
    "diet_type": "Vegetarian",
    "cuisine": "Southern",
    "time_to_eat": 60,
    "suggestion_links": [
        "https://www.allrecipes.com/recipe/39932/american-girls-peach-cobbler/",
        "https://www.allrecipes.com/recipe/22993/peach-cobbler-ii/",
        "https://www.allrecipes.com/recipe/18469/peach-cobbler-vi/",
        "https://www.allrecipes.com/recipe/234306/butter-biscuit-peach-cobbler/",
        "https://www.allrecipes.com/recipe/19897/old-fashioned-peach-cobbler/"
    ],
    "img_links": [
        "https://www.allrecipes.com/thmb/EKHEazOTzCRl0lXI4N8J71M0BGM=/1500x0/filters:no_upscale():max_bytes(150000):strip_icc()/4014817-f0b224c442ca4843bbaec4634f309717.jpg"
    ],
    "source_url": "https://www.allrecipes.com/recipe/22778/southern-peach-cobbler/",
    "id": "d5591c55-e704-48d4-a4fb-63be0d162b0a"
}